dbaas_foxha/__init__.py
dbaas_foxha/dbaas_api.py
dbaas_foxha/provider.py
dbaas_foxha-0.3.0.dist-info/LICENSE
dbaas_foxha-0.3.0.dist-info/METADATA
dbaas_foxha-0.3.0.dist-info/WHEEL
dbaas_foxha-0.3.0.dist-info/top_level.txt
dbaas_foxha-0.3.0.dist-info/RECORD
