Metadata-Version: 2.1
Name: dbaas-foxha
Version: 0.3.0
Summary: DBaaS FoxHA is a simple FoxHA api wrapper for DBaaS
Home-page: https://github.com/globocom/dbaas-foxha
Author: Mauro Murari
Author-email: mauro_murari@hotmail.com
License: UNKNOWN
Keywords: dbaas_foxha
Platform: UNKNOWN
Classifier: Development Status :: 2 - Pre-Alpha
Classifier: Intended Audience :: Developers
Classifier: Natural Language :: English
Classifier: Programming Language :: Python :: 2
Classifier: Programming Language :: Python :: 2.6
Classifier: Programming Language :: Python :: 2.7
Classifier: Programming Language :: Python :: 3
Classifier: Programming Language :: Python :: 3.3
Classifier: Programming Language :: Python :: 3.4
Classifier: Programming Language :: Python :: 3.5
Requires-Dist: foxha (==0.9.3)
Requires-Dist: dbaas-credentials (>=1.1.3)
